flask_sqlalchemy/__init__.py
flask_sqlalchemy/cli.py
flask_sqlalchemy/extension.py
flask_sqlalchemy/model.py
flask_sqlalchemy/pagination.py
flask_sqlalchemy/py.typed
flask_sqlalchemy/query.py
flask_sqlalchemy/record_queries.py
flask_sqlalchemy/session.py
flask_sqlalchemy/table.py
flask_sqlalchemy/track_modifications.py
flask_sqlalchemy/version.py
flask_sqlalchemy_py37/__init__.py
flask_sqlalchemy_py37/cli.py
flask_sqlalchemy_py37/extension.py
flask_sqlalchemy_py37/model.py
flask_sqlalchemy_py37/pagination.py
flask_sqlalchemy_py37/py.typed
flask_sqlalchemy_py37/query.py
flask_sqlalchemy_py37/record_queries.py
flask_sqlalchemy_py37/session.py
flask_sqlalchemy_py37/table.py
flask_sqlalchemy_py37/track_modifications.py
flask_sqlalchemy_py37/version.py
Flask_SQLAlchemy_compat_backend_py37-3.1.0.dev3.dist-info/LICENSE.rst
Flask_SQLAlchemy_compat_backend_py37-3.1.0.dev3.dist-info/METADATA
Flask_SQLAlchemy_compat_backend_py37-3.1.0.dev3.dist-info/WHEEL
Flask_SQLAlchemy_compat_backend_py37-3.1.0.dev3.dist-info/top_level.txt
Flask_SQLAlchemy_compat_backend_py37-3.1.0.dev3.dist-info/zip-safe
Flask_SQLAlchemy_compat_backend_py37-3.1.0.dev3.dist-info/RECORD
