Metadata-Version: 2.1
Name: Flask-SQLAlchemy-compat-backend-py37
Version: 3.1.0.dev3
Summary: Flask SQLAlchemy backend supporting the Python 3.7 version of Flask SQLAlchemy compat.
Maintainer-email: Pallets <contact@palletsprojects.com>
License: Copyright 2010 Pallets
Project-URL: Donate, https://palletsprojects.com/donate
Project-URL: Documentation, https://flask-sqlalchemy.palletsprojects.com
Project-URL: Changes, https://flask-sqlalchemy.palletsprojects.com/changes/
Project-URL: Source Code, https://github.com/pallets-eco/flask-sqlalchemy/
Project-URL: Issue Tracker, https://github.com/pallets-eco/flask-sqlalchemy/issues/
Project-URL: Chat, https://discord.gg/pallets
Classifier: Development Status :: 5 - Production/Stable
Classifier: Environment :: Web Environment
Classifier: Intended Audience :: Developers
Classifier: License :: OSI Approved :: BSD License
Classifier: Operating System :: OS Independent
Classifier: Programming Language :: Python
Classifier: Programming Language :: Python :: 3 :: Only
Classifier: Programming Language :: Python :: 3.7
Classifier: Topic :: Internet :: WWW/HTTP :: Dynamic Content
Requires-Python: <3.8,>=3.7
License-File: LICENSE.rst
Requires-Dist: flask>=2.2.5
Requires-Dist: sqlalchemy>=2.0.0
Requires-Dist: flask-sqlalchemy
